magnetoo/__init__.py
magnetoo/main.py
magnetoo-0.1.0.dist-info/licenses/LICENSE
magnetoo-0.1.0.dist-info/METADATA
magnetoo-0.1.0.dist-info/WHEEL
magnetoo-0.1.0.dist-info/entry_points.txt
magnetoo-0.1.0.dist-info/top_level.txt
magnetoo-0.1.0.dist-info/RECORD
