Metadata-Version: 2.4
Name: magnetoo
Version: 0.1.0
Summary: find the best magnet links for your torrents on your terminal!
Author-email: Kanishk Pachauri <itskanishkp.py@gmail.com>
License: MIT
Project-URL: Homepage, https://github.com/homelabshq/magnetoo
Project-URL: Repository, https://github.com/homelabshq/magnetoo
Project-URL: Issues, https://github.com/homelabshq/magnetoo/issues
Keywords: magnet,torrent,cli,commandline,magnet-finder,magnetoo
Classifier: License :: OSI Approved :: MIT License
Classifier: Programming Language :: Python
Classifier: Programming Language :: Python :: 3
Classifier: Programming Language :: Python :: 3.10
Classifier: Programming Language :: Python :: 3.11
Classifier: Programming Language :: Python :: 3.12
Classifier: Programming Language :: Python :: 3.13
Classifier: Programming Language :: Python :: 3.14
Classifier: Environment :: Console
Classifier: Topic :: System :: Shells
Classifier: Topic :: Terminals
Requires-Python: >=3.10
License-File: LICENSE
Requires-Dist: requests>=2.32.5
Dynamic: license-file
